{"DOS_HEADER":{"e_magic":23117,"e_cblp":144,"e_cp":3,"e_crlc":0,"e_cparhdr":4,"e_minalloc":0,"e_maxalloc":65535,"e_ss":0,"e_sp":184,"e_csum":0,"e_ip":0,"e_cs":0,"e_lfarlc":64,"e_ovno":0,"e_res":"","e_oemid":0,"e_oeminfo":0,"e_res2":"","e_lfanew":176},"NT_HEADERS":{"Signature":17744},"FILE_HEADER":{"Machine":332,"NumberOfSections":1,"TimeDateStamp":0,"PointerToSymbolTable":0,"NumberOfSymbols":0,"SizeOfOptionalHeader":224,"Characteristics":258},"OPTIONAL_HEADER":{"Magic":267,"MajorLinkerVersion":3,"MinorLinkerVersion":0,"SizeOfCode":0,"SizeOfInitializedData":0,"SizeOfUninitializedData":0,"AddressOfEntryPoint":10901,"BaseOfCode":0,"BaseOfData":0,"ImageBase":4194304,"SectionAlignment":4096,"FileAlignment":512,"MajorOperatingSystemVersion":0,"MinorOperatingSystemVersion":0,"MajorImageVersion":0,"MinorImageVersion":0,"MajorSubsystemVersion":4,"MinorSubsystemVersion":0,"Reserved1":0,"SizeOfImage":20480,"SizeOfHeaders":464,"CheckSum":33313,"Subsystem":3,"DllCharacteristics":0,"SizeOfStackReserve":0,"SizeOfStackCommit":0,"SizeOfHeapReserve":0,"SizeOfHeapCommit":0,"LoaderFlags":0,"NumberOfRvaAndSizes":16,"DATA_DIRECTORY":{"IMAGE_DIRECTORY_ENTRY_EXPORT":{"VirtualAddress":11712,"Size":304},"IMAGE_DIRECTORY_ENTRY_IMPORT":{"VirtualAddress":11328,"Size":0},"IMAGE_DIRECTORY_ENTRY_RESOURCE":{"VirtualAddress":4096,"Size":0},"IMAGE_DIRECTORY_ENTRY_EXCEPTION":{"VirtualAddress":12176,"Size":12},"IMAGE_DIRECTORY_ENTRY_SECURITY":{"VirtualAddress":8704,"Size":2176},"IMAGE_DIRECTORY_ENTRY_BASERELOC":{"VirtualAddress":12208,"Size":10},"IMAGE_DIRECTORY_ENTRY_DEBUG":{"VirtualAddress":0,"Size":0},"IMAGE_DIRECTORY_ENTRY_COPYRIGHT":{"VirtualAddress":11680,"Size":20},"IMAGE_DIRECTORY_ENTRY_GLOBALPTR":{"VirtualAddress":0,"Size":0},"IMAGE_DIRECTORY_ENTRY_TLS":{"VirtualAddress":12016,"Size":0},"IMAGE_DIRECTORY_ENTRY_LOAD_CONFIG":{"VirtualAddress":12064,"Size":64},"IMAGE_DIRECTORY_ENTRY_BOUND_IMPORT":{"VirtualAddress":0,"Size":0},"IMAGE_DIRECTORY_ENTRY_IAT":{"VirtualAddress":11568,"Size":48},"IMAGE_DIRECTORY_ENTRY_DELAY_IMPORT":{"VirtualAddress":0,"Size":0},"IMAGE_DIRECTORY_ENTRY_COM_DESCRIPTOR":{"VirtualAddress":0,"Size":0},"IMAGE_DIRECTORY_ENTRY_RESERVED":{"VirtualAddress":0,"Size":0}}},"SECTIONS":[{"Name":"","Misc":16384,"VirtualAddress":4096,"SizeOfRawData":8192,"PointerToRawData":512,"PointerToRelocations":0,"PointerToLinenumbers":0,"NumberOfRelocations":0,"NumberOfLinenumbers":0,"Characteristics":2684354560,"entropy":5.5418}],"IMPORTS":[{"dll":"kernel32.dll","struct":{"OriginalFirstThunk":11440,"TimeDateStamp":0,"ForwarderChain":0,"Name":11616,"FirstThunk":11568},"imports":[{"address":4205872,"name":"ExitProcess","ordinal":null,"import_by_ordinal":false,"hint":0},{"address":4205876,"name":"CreateActCtxA","ordinal":null,"import_by_ordinal":false,"hint":0}]},{"dll":"msvcrt.dll","struct":{"OriginalFirstThunk":11464,"TimeDateStamp":0,"ForwarderChain":0,"Name":11629,"FirstThunk":11592},"imports":[{"address":4205896,"name":"printf","ordinal":null,"import_by_ordinal":false,"hint":0}]},{"dll":"user32.dll","struct":{"OriginalFirstThunk":11452,"TimeDateStamp":0,"ForwarderChain":0,"Name":11640,"FirstThunk":11580},"imports":[{"address":4205884,"name":"LoadIconA","ordinal":null,"import_by_ordinal":false,"hint":0},{"address":4205888,"name":"LoadStringA","ordinal":null,"import_by_ordinal":false,"hint":0}]},{"dll":"standard.exe","struct":{"OriginalFirstThunk":11472,"TimeDateStamp":0,"ForwarderChain":0,"Name":11651,"FirstThunk":11600},"imports":[{"address":4205904,"name":"export","ordinal":null,"import_by_ordinal":false,"hint":0}]}],"EXPORTS":{"struct":{"Characteristics":0,"TimeDateStamp":0,"MajorVersion":0,"MinorVersion":0,"Name":0,"Base":0,"NumberOfFunctions":7,"NumberOfNames":7,"AddressOfFunctions":11760,"AddressOfNames":11792,"AddressOfNameOrdinals":11936},"symbols":[{"address":11824,"name":"ExitProcess","ordinal":0,"forwarder":"standard.LoopHere"},{"address":11842,"name":"LoopHere","ordinal":1,"forwarder":"standard.LoopOnceAgain"},{"address":11865,"name":"LoopOnceAgain","ordinal":2,"forwarder":"msvcrt.printf"},{"address":11879,"name":"GroundHogDay","ordinal":3,"forwarder":"standard.GroundHogDay"},{"address":11915,"name":"Ying","ordinal":4,"forwarder":"standard.Yang"},{"address":11901,"name":"Yang","ordinal":5,"forwarder":"standard.Ying"},{"address":10913,"name":"export","ordinal":6,"forwarder":null}]},"RESOURCES":[{"id":3,"directory":[{"id":1576,"directory":[{"id":0,"data":{"struct":{"OffsetToData":4480,"Size":5672,"CodePage":0,"Reserved":0},"lang":0,"sublang":0}}]}]},{"id":6,"directory":[{"id":10,"directory":[{"id":0,"data":{"struct":{"OffsetToData":10768,"Size":76,"CodePage":0,"Reserved":0},"lang":0,"sublang":0}}]}]},{"id":14,"directory":[{"id":788,"directory":[{"id":0,"data":{"struct":{"OffsetToData":10160,"Size":20,"CodePage":0,"Reserved":0},"lang":0,"sublang":0}}]}]},{"id":16,"directory":[{"id":1,"directory":[{"id":0,"data":{"struct":{"OffsetToData":10192,"Size":452,"CodePage":0,"Reserved":0},"lang":0,"sublang":0}}]}]},{"id":24,"directory":[{"id":1,"directory":[{"id":0,"data":{"struct":{"OffsetToData":10656,"Size":74,"CodePage":0,"Reserved":0},"lang":0,"sublang":0}}]}]}],"RELOCATIONS":[{"struct":{"VirtualAddress":10901,"SizeOfBlock":10},"entries":[{"rva":10902,"type":0}]}],"TLS":{"struct":{"StartAddressOfRawData":0,"EndAddressOfRawData":0,"AddressOfIndex":4205206,"AddressOfCallBacks":4206352,"SizeOfZeroFill":0,"Characteristics":0},"callbacks":[]},"DEBUG":[],"LOAD_CONFIG":{"Size":92,"TimeDateStamp":0,"MajorVersion":0,"MinorVersion":0,"GlobalFlagsClear":0,"GlobalFlagsSet":0,"CriticalSectionDefaultTimeout":0,"DeCommitFreeBlockThreshold":0,"DeCommitTotalFreeThreshold":0,"LockPrefixTable":0,"MaximumAllocationSize":0,"VirtualMemoryThreshold":0,"ProcessHeapFlags":0,"ProcessAffinityMask":0,"CSDVersion":0,"DependentLoadFlags":0,"EditList":0,"SecurityCookie":4206460,"SEHandlerTable":4206464,"SEHandlerCount":1,"GuardCFCheckFunctionPointer":0,"GuardCFDispatchFunctionPointer":0,"GuardCFFunctionTable":0,"GuardCFFunctionCount":0,"GuardFlags":0},"BOUND_IMPORTS":[],"DELAY_IMPORTS":[]}